<?xml version="1.0" encoding="utf-8"?>
<CARDGEN>
    <CARDSUM>
        <DATA_FORMAT_VERSION>10</DATA_FORMAT_VERSION>
        <FILEDATE>21-10-2022</FILEDATE>
        <FILETIME>04-30-18</FILETIME>
        <NO_OF_CARRIERS>1</NO_OF_CARRIERS>
        <NO_OF_CARDS>1</NO_OF_CARDS>
        <NO_OF_PRODUCTS>1</NO_OF_PRODUCTS>
        <TXREF>61003</TXREF>
        <ORDER_REF />
    </CARDSUM>
    <PRODUCT>
        <PRODUCT_REF>VAULTBLACKSTD001</PRODUCT_REF>
        <RECORD>
            <REQUEST_TYPE>New</REQUEST_TYPE>
            <UID>1</UID>
            <CARRIER>
                <TITLE>MRS</TITLE>
                <FNAME>Minnie</FNAME>
                <SNAME>Mouse</SNAME>
                <ADD1>1430 Ellice Street</ADD1>
                <ADD2>Winnipeg, MB</ADD2>
                <ADD3 />
                <ADD4 />
                <CITY>Winnipeg</CITY>
                <POSTCODE>R3G 0G4</POSTCODE>
                <COUNTRY>124</COUNTRY>
                <BULK_ADD1>1420 Ellice Street</BULK_ADD1>
                <BULK_ADD2>Winnipeg MB</BULK_ADD2>
                <BULK_ADD3 />
                <BULK_CITY>Winnipeg</BULK_CITY>
                <BULK_COUNTY />
                <BULK_POSTCODE>R3G 0G4</BULK_POSTCODE>
                <BULK_COUNTRY>124</BULK_COUNTRY>
                <CARRIER_TYPE>VLT</CARRIER_TYPE>
                <CARRIER_LOGO_ID />
                <DELV_METHOD>4</DELV_METHOD>
                <DELV_CODE />
                <FULFIL1 />
                <FULFIL2 />
                <LANG />
            </CARRIER>
            <CARD>
                <TYPE>Chip&amp;Mag</TYPE>
                <CURRENCY>0124</CURRENCY>
                <TRACK1>B5206906732278501^TEST3/^2609221000004550000000</TRACK1>
                <TRACK2>5206906732278501=26092210000004845500</TRACK2>
                <TRACK3>108947764</TRACK3>
                <EMBOSS_PAN>5206 9067 3227 8501</EMBOSS_PAN>
                <EMBOSS_NAME>TEST3</EMBOSS_NAME>
                <EMBOSS_START>10/22</EMBOSS_START>
                <EMBOSS_EXPIRY>09/26</EMBOSS_EXPIRY>
                <EMBOSS_CVC2>669</EMBOSS_CVC2>
                <EMBOSS_LINE4>108947764</EMBOSS_LINE4>
                <THERMAL_LINE1>RANDOM COMPANY 1</THERMAL_LINE1>
                <THERMAL_LINE2 />
                <IMAGE_ID />
                <LOGO_FRONT_ID />
                <LOGO_BACK_ID />
                <QRCODE />
                <CHIP>
                    <TYPE>Mastercard</TYPE>
                    <PAN>5206906732278501</PAN>
                    <PAN_SEQ>00</PAN_SEQ>
                    <NAME>TEST3/</NAME>
                    <START_DATE>221001</START_DATE>
                    <EXPIRY_DATE>260930</EXPIRY_DATE>
                    <SERVICE_CODE>221</SERVICE_CODE>
                    <CHIP_TRACK_1>B5206906732278501^TEST3/^2609221000002700000000</CHIP_TRACK_1>
                    <CHIP_TRACK_2>5206906732278501D26092210000004827000F</CHIP_TRACK_2>
                    <CHIP_TRACK_1_MSD_CL>B5206906732278501^ /^2609221000002700000000</CHIP_TRACK_1_MSD_CL>
                    <CHIP_TRACK_2_MSD_CL />
                    <PINBLOCK>BB073B166B89F5DB</PINBLOCK>
                </CHIP>
            </CARD>
        </RECORD>
        <RECORD>
            <REQUEST_TYPE>New</REQUEST_TYPE>
            <UID>2</UID>
            <CARRIER>
                <TITLE>MRS</TITLE>
                <FNAME>Minnie</FNAME>
                <SNAME>Mouse</SNAME>
                <ADD1>1430 Ellice Street</ADD1>
                <ADD2>Winnipeg, MB</ADD2>
                <ADD3 />
                <ADD4 />
                <CITY>Winnipeg</CITY>
                <POSTCODE>R3G 0G4</POSTCODE>
                <COUNTRY>124</COUNTRY>
                <BULK_ADD1>1420 Ellice Street</BULK_ADD1>
                <BULK_ADD2>Winnipeg MB</BULK_ADD2>
                <BULK_ADD3 />
                <BULK_CITY>Winnipeg</BULK_CITY>
                <BULK_COUNTY />
                <BULK_POSTCODE>R3G 0G4</BULK_POSTCODE>
                <BULK_COUNTRY>124</BULK_COUNTRY>
                <CARRIER_TYPE>VLT</CARRIER_TYPE>
                <CARRIER_LOGO_ID />
                <DELV_METHOD>4</DELV_METHOD>
                <DELV_CODE />
                <FULFIL1 />
                <FULFIL2 />
                <LANG />
            </CARRIER>
            <CARD>
                <TYPE>Chip&amp;Mag</TYPE>
                <CURRENCY>0124</CURRENCY>
                <TRACK1>B5206906732278501^TEST3/^2609221000004550000000</TRACK1>
                <TRACK2>5206906732278501=26092210000004845500</TRACK2>
                <TRACK3>108947764</TRACK3>
                <EMBOSS_PAN>5206 9067 3227 8501</EMBOSS_PAN>
                <EMBOSS_NAME>TEST3</EMBOSS_NAME>
                <EMBOSS_START>10/22</EMBOSS_START>
                <EMBOSS_EXPIRY>09/26</EMBOSS_EXPIRY>
                <EMBOSS_CVC2>669</EMBOSS_CVC2>
                <EMBOSS_LINE4>108947764</EMBOSS_LINE4>
                <THERMAL_LINE1>RANDOM COMPANY 1</THERMAL_LINE1>
                <THERMAL_LINE2 />
                <IMAGE_ID />
                <LOGO_FRONT_ID />
                <LOGO_BACK_ID />
                <QRCODE />
                <CHIP>
                    <TYPE>Mastercard</TYPE>
                    <PAN>5206906732278501</PAN>
                    <PAN_SEQ>00</PAN_SEQ>
                    <NAME>TEST3/</NAME>
                    <START_DATE>221001</START_DATE>
                    <EXPIRY_DATE>260930</EXPIRY_DATE>
                    <SERVICE_CODE>221</SERVICE_CODE>
                    <CHIP_TRACK_1>B5206906732278501^TEST3/^2609221000002700000000</CHIP_TRACK_1>
                    <CHIP_TRACK_2>5206906732278501D26092210000004827000F</CHIP_TRACK_2>
                    <CHIP_TRACK_1_MSD_CL>B5206906732278501^ /^2609221000002700000000</CHIP_TRACK_1_MSD_CL>
                    <CHIP_TRACK_2_MSD_CL />
                    <PINBLOCK>BB073B166B89F5DB</PINBLOCK>
                </CHIP>
            </CARD>
        </RECORD>
    </PRODUCT>
    <PRODUCT>
        <PRODUCT_REF>VAULTBLACKSTD002</PRODUCT_REF>
        <RECORD>
            <REQUEST_TYPE>New</REQUEST_TYPE>
            <UID>3</UID>
            <CARRIER>
                <TITLE>MRS</TITLE>
                <FNAME>Minnie</FNAME>
                <SNAME>Mouse</SNAME>
                <ADD1>1430 Ellice Street</ADD1>
                <ADD2>Winnipeg, MB</ADD2>
                <ADD3 />
                <ADD4 />
                <CITY>Winnipeg</CITY>
                <POSTCODE>R3G 0G4</POSTCODE>
                <COUNTRY>124</COUNTRY>
                <BULK_ADD1>1420 Ellice Street</BULK_ADD1>
                <BULK_ADD2>Winnipeg MB</BULK_ADD2>
                <BULK_ADD3 />
                <BULK_CITY>Winnipeg</BULK_CITY>
                <BULK_COUNTY />
                <BULK_POSTCODE>R3G 0G4</BULK_POSTCODE>
                <BULK_COUNTRY>124</BULK_COUNTRY>
                <CARRIER_TYPE>VLT</CARRIER_TYPE>
                <CARRIER_LOGO_ID />
                <DELV_METHOD>4</DELV_METHOD>
                <DELV_CODE />
                <FULFIL1 />
                <FULFIL2 />
                <LANG />
            </CARRIER>
            <CARD>
                <TYPE>Chip&amp;Mag</TYPE>
                <CURRENCY>0124</CURRENCY>
                <TRACK1>B5206906732278501^TEST3/^2609221000004550000000</TRACK1>
                <TRACK2>5206906732278501=26092210000004845500</TRACK2>
                <TRACK3>108947764</TRACK3>
                <EMBOSS_PAN>5206 9067 3227 8501</EMBOSS_PAN>
                <EMBOSS_NAME>TEST3</EMBOSS_NAME>
                <EMBOSS_START>10/22</EMBOSS_START>
                <EMBOSS_EXPIRY>09/26</EMBOSS_EXPIRY>
                <EMBOSS_CVC2>669</EMBOSS_CVC2>
                <EMBOSS_LINE4>108947764</EMBOSS_LINE4>
                <THERMAL_LINE1>RANDOM COMPANY 1</THERMAL_LINE1>
                <THERMAL_LINE2 />
                <IMAGE_ID />
                <LOGO_FRONT_ID />
                <LOGO_BACK_ID />
                <QRCODE />
                <CHIP>
                    <TYPE>Mastercard</TYPE>
                    <PAN>5206906732278501</PAN>
                    <PAN_SEQ>00</PAN_SEQ>
                    <NAME>TEST3/</NAME>
                    <START_DATE>221001</START_DATE>
                    <EXPIRY_DATE>260930</EXPIRY_DATE>
                    <SERVICE_CODE>221</SERVICE_CODE>
                    <CHIP_TRACK_1>B5206906732278501^TEST3/^2609221000002700000000</CHIP_TRACK_1>
                    <CHIP_TRACK_2>5206906732278501D26092210000004827000F</CHIP_TRACK_2>
                    <CHIP_TRACK_1_MSD_CL>B5206906732278501^ /^2609221000002700000000</CHIP_TRACK_1_MSD_CL>
                    <CHIP_TRACK_2_MSD_CL />
                    <PINBLOCK>BB073B166B89F5DB</PINBLOCK>
                </CHIP>
            </CARD>
        </RECORD>
        <RECORD>
            <REQUEST_TYPE>New</REQUEST_TYPE>
            <UID>4</UID>
            <CARRIER>
                <TITLE>MRS</TITLE>
                <FNAME>Minnie</FNAME>
                <SNAME>Mouse</SNAME>
                <ADD1>1430 Ellice Street</ADD1>
                <ADD2>Winnipeg, MB</ADD2>
                <ADD3 />
                <ADD4 />
                <CITY>Winnipeg</CITY>
                <POSTCODE>R3G 0G4</POSTCODE>
                <COUNTRY>124</COUNTRY>
                <BULK_ADD1>1420 Ellice Street</BULK_ADD1>
                <BULK_ADD2>Winnipeg MB</BULK_ADD2>
                <BULK_ADD3 />
                <BULK_CITY>Winnipeg</BULK_CITY>
                <BULK_COUNTY />
                <BULK_POSTCODE>R3G 0G4</BULK_POSTCODE>
                <BULK_COUNTRY>124</BULK_COUNTRY>
                <CARRIER_TYPE>VLT</CARRIER_TYPE>
                <CARRIER_LOGO_ID />
                <DELV_METHOD>4</DELV_METHOD>
                <DELV_CODE />
                <FULFIL1 />
                <FULFIL2 />
                <LANG />
            </CARRIER>
            <CARD>
                <TYPE>Chip&amp;Mag</TYPE>
                <CURRENCY>0124</CURRENCY>
                <TRACK1>B5206906732278501^TEST3/^2609221000004550000000</TRACK1>
                <TRACK2>5206906732278501=26092210000004845500</TRACK2>
                <TRACK3>108947764</TRACK3>
                <EMBOSS_PAN>5206 9067 3227 8501</EMBOSS_PAN>
                <EMBOSS_NAME>TEST3</EMBOSS_NAME>
                <EMBOSS_START>10/22</EMBOSS_START>
                <EMBOSS_EXPIRY>09/26</EMBOSS_EXPIRY>
                <EMBOSS_CVC2>669</EMBOSS_CVC2>
                <EMBOSS_LINE4>108947764</EMBOSS_LINE4>
                <THERMAL_LINE1>RANDOM COMPANY 1</THERMAL_LINE1>
                <THERMAL_LINE2 />
                <IMAGE_ID />
                <LOGO_FRONT_ID />
                <LOGO_BACK_ID />
                <QRCODE />
                <CHIP>
                    <TYPE>Mastercard</TYPE>
                    <PAN>5206906732278501</PAN>
                    <PAN_SEQ>00</PAN_SEQ>
                    <NAME>TEST3/</NAME>
                    <START_DATE>221001</START_DATE>
                    <EXPIRY_DATE>260930</EXPIRY_DATE>
                    <SERVICE_CODE>221</SERVICE_CODE>
                    <CHIP_TRACK_1>B5206906732278501^TEST3/^2609221000002700000000</CHIP_TRACK_1>
                    <CHIP_TRACK_2>5206906732278501D26092210000004827000F</CHIP_TRACK_2>
                    <CHIP_TRACK_1_MSD_CL>B5206906732278501^ /^2609221000002700000000</CHIP_TRACK_1_MSD_CL>
                    <CHIP_TRACK_2_MSD_CL />
                    <PINBLOCK>BB073B166B89F5DB</PINBLOCK>
                </CHIP>
            </CARD>
    </RECORD>
    </PRODUCT>
    <PRODUCT>
        <PRODUCT_REF>VAULTBLACKSTD003</PRODUCT_REF>
    <RECORD>
            <REQUEST_TYPE>USED</REQUEST_TYPE>
            <UID>5</UID>
            <CARRIER>
                <TITLE>MRS</TITLE>
                <FNAME>Minnie</FNAME>
                <SNAME>Mouse</SNAME>
                <ADD1>1430 Ellice Street</ADD1>
                <ADD2>Winnipeg, MB</ADD2>
                <ADD3 />
                <ADD4 />
                <CITY>Winnipeg</CITY>
                <POSTCODE>R3G 0G4</POSTCODE>
                <COUNTRY>124</COUNTRY>
                <BULK_ADD1>1420 Ellice Street</BULK_ADD1>
                <BULK_ADD2>Winnipeg MB</BULK_ADD2>
                <BULK_ADD3 />
                <BULK_CITY>Winnipeg</BULK_CITY>
                <BULK_COUNTY />
                <BULK_POSTCODE>R3G 0G4</BULK_POSTCODE>
                <BULK_COUNTRY>124</BULK_COUNTRY>
                <CARRIER_TYPE>VLT</CARRIER_TYPE>
                <CARRIER_LOGO_ID />
                <DELV_METHOD>4</DELV_METHOD>
                <DELV_CODE />
                <FULFIL1 />
                <FULFIL2 />
                <LANG />
            </CARRIER>
            <CARD>
                <TYPE>Chip&amp;Mag</TYPE>
                <CURRENCY>0124</CURRENCY>
                <TRACK1>B5206906732278501^TEST3/^2609221000004550000000</TRACK1>
                <TRACK2>5206906732278501=26092210000004845500</TRACK2>
                <TRACK3>108947764</TRACK3>
                <EMBOSS_PAN>5206 9067 3227 8501</EMBOSS_PAN>
                <EMBOSS_NAME>TEST3</EMBOSS_NAME>
                <EMBOSS_START>10/22</EMBOSS_START>
                <EMBOSS_EXPIRY>09/26</EMBOSS_EXPIRY>
                <EMBOSS_CVC2>669</EMBOSS_CVC2>
                <EMBOSS_LINE4>108947764</EMBOSS_LINE4>
                <THERMAL_LINE1>RANDOM COMPANY 1</THERMAL_LINE1>
                <THERMAL_LINE2 />
                <IMAGE_ID />
                <LOGO_FRONT_ID />
                <LOGO_BACK_ID />
                <QRCODE />
                <CHIP>
                    <TYPE>Mastercard</TYPE>
                    <PAN>5206906732278501</PAN>
                    <PAN_SEQ>00</PAN_SEQ>
                    <NAME>TEST3/</NAME>
                    <START_DATE>221001</START_DATE>
                    <EXPIRY_DATE>260930</EXPIRY_DATE>
                    <SERVICE_CODE>221</SERVICE_CODE>
                    <CHIP_TRACK_1>B5206906732278501^TEST3/^2609221000002700000000</CHIP_TRACK_1>
                    <CHIP_TRACK_2>5206906732278501D26092210000004827000F</CHIP_TRACK_2>
                    <CHIP_TRACK_1_MSD_CL>B5206906732278501^ /^2609221000002700000000</CHIP_TRACK_1_MSD_CL>
                    <CHIP_TRACK_2_MSD_CL />
                    <PINBLOCK>BB073B166B89F5DB</PINBLOCK>
                </CHIP>
            </CARD>
        </RECORD>
    </PRODUCT>
</CARDGEN>